{
    "player_score": 8,
    "opponent_score": 3,
    "game_score": [
        0,
        0
    ],
    "set_score": [
        0,
        0
    ],
    "stats": {
        "First Serve Winners": [
            0,
            0
        ],
        "Second Serve Winners": [
            0,
            0
        ],
        "First Serve Aces": [
            0,
            0
        ],
        "Second Serve Aces": [
            0,
            0
        ],
        "First Serve Volleys": [
            8,
            0
        ],
        "Second Serve Volleys": [
            0,
            1
        ],
        "Double Faults": [
            2,
            0
        ]
    },
    "timestamp": "2025-06-03 23:30:40"
}